{
    "os": "Linux-5.10.0-23-amd64-x86_64-with-glibc2.31",
    "python": "3.9.2",
    "heartbeatAt": "2023-11-10T10:54:32.286410",
    "startedAt": "2023-11-10T10:54:31.203713",
    "docker": null,
    "cuda": null,
    "args": [
        "--debug",
        "--load_cached_flows",
        "--force",
        "--wandb"
    ],
    "state": "running",
    "program": "/users/ug21/jvaditya/CS337_Project/CS337_HCR/video_style.py",
    "codePathLocal": "video_style.py",
    "codePath": "video_style.py",
    "git": {
        "remote": "https://github.com/AnanthKidambi/CS337_HCR.git",
        "commit": "091dc98dd519d04871987467d1afdef41a879de8"
    },
    "email": null,
    "root": "/users/ug21/jvaditya/CS337_Project/CS337_HCR",
    "host": "gpu1",
    "username": "jvaditya",
    "executable": "/users/ug21/jvaditya/CS337_Project/bin/python",
    "cpu_count": 48,
    "cpu_count_logical": 96,
    "cpu_freq": {
        "current": 1005.5814166666672,
        "min": 1000.0,
        "max": 4000.0
    },
    "cpu_freq_per_core": [
        {
            "current": 1000.087,
            "min": 1000.0,
            "max": 4000.0
        },
        {
            "current": 1000.615,
            "min": 1000.0,
            "max": 4000.0
        },
        {
            "current": 1000.191,
            "min": 1000.0,
            "max": 4000.0
        },
        {
            "current": 999.928,
            "min": 1000.0,
            "max": 4000.0
        },
        {
            "current": 1000.576,
            "min": 1000.0,
            "max": 4000.0
        },
        {
            "current": 1000.49,
            "min": 1000.0,
            "max": 4000.0
        },
        {
            "current": 1000.322,
            "min": 1000.0,
            "max": 4000.0
        },
        {
            "current": 1000.356,
            "min": 1000.0,
            "max": 4000.0
        },
        {
            "current": 1000.554,
            "min": 1000.0,
            "max": 4000.0
        },
        {
            "current": 1000.212,
            "min": 1000.0,
            "max": 4000.0
        },
        {
            "current": 999.884,
            "min": 1000.0,
            "max": 4000.0
        },
        {
            "current": 1000.858,
            "min": 1000.0,
            "max": 4000.0
        },
        {
            "current": 1000.142,
            "min": 1000.0,
            "max": 4000.0
        },
        {
            "current": 1000.632,
            "min": 1000.0,
            "max": 4000.0
        },
        {
            "current": 999.919,
            "min": 1000.0,
            "max": 4000.0
        },
        {
            "current": 1000.472,
            "min": 1000.0,
            "max": 4000.0
        },
        {
            "current": 1000.397,
            "min": 1000.0,
            "max": 4000.0
        },
        {
            "current": 1001.062,
            "min": 1000.0,
            "max": 4000.0
        },
        {
            "current": 999.974,
            "min": 1000.0,
            "max": 4000.0
        },
        {
            "current": 1001.021,
            "min": 1000.0,
            "max": 4000.0
        },
        {
            "current": 1000.578,
            "min": 1000.0,
            "max": 4000.0
        },
        {
            "current": 1000.77,
            "min": 1000.0,
            "max": 4000.0
        },
        {
            "current": 1000.839,
            "min": 1000.0,
            "max": 4000.0
        },
        {
            "current": 1000.314,
            "min": 1000.0,
            "max": 4000.0
        },
        {
            "current": 1000.43,
            "min": 1000.0,
            "max": 4000.0
        },
        {
            "current": 1000.339,
            "min": 1000.0,
            "max": 4000.0
        },
        {
            "current": 1000.247,
            "min": 1000.0,
            "max": 4000.0
        },
        {
            "current": 1000.927,
            "min": 1000.0,
            "max": 4000.0
        },
        {
            "current": 1000.49,
            "min": 1000.0,
            "max": 4000.0
        },
        {
            "current": 1000.136,
            "min": 1000.0,
            "max": 4000.0
        },
        {
            "current": 1000.351,
            "min": 1000.0,
            "max": 4000.0
        },
        {
            "current": 1000.666,
            "min": 1000.0,
            "max": 4000.0
        },
        {
            "current": 1785.275,
            "min": 1000.0,
            "max": 4000.0
        },
        {
            "current": 999.987,
            "min": 1000.0,
            "max": 4000.0
        },
        {
            "current": 1000.057,
            "min": 1000.0,
            "max": 4000.0
        },
        {
            "current": 1000.461,
            "min": 1000.0,
            "max": 4000.0
        },
        {
            "current": 999.923,
            "min": 1000.0,
            "max": 4000.0
        },
        {
            "current": 1725.411,
            "min": 1000.0,
            "max": 4000.0
        },
        {
            "current": 999.915,
            "min": 1000.0,
            "max": 4000.0
        },
        {
            "current": 1000.263,
            "min": 1000.0,
            "max": 4000.0
        },
        {
            "current": 999.911,
            "min": 1000.0,
            "max": 4000.0
        },
        {
            "current": 1000.403,
            "min": 1000.0,
            "max": 4000.0
        },
        {
            "current": 1000.477,
            "min": 1000.0,
            "max": 4000.0
        },
        {
            "current": 1000.943,
            "min": 1000.0,
            "max": 4000.0
        },
        {
            "current": 1000.311,
            "min": 1000.0,
            "max": 4000.0
        },
        {
            "current": 1000.56,
            "min": 1000.0,
            "max": 4000.0
        },
        {
            "current": 1000.622,
            "min": 1000.0,
            "max": 4000.0
        },
        {
            "current": 1000.729,
            "min": 1000.0,
            "max": 4000.0
        },
        {
            "current": 1000.513,
            "min": 1000.0,
            "max": 4000.0
        },
        {
            "current": 1000.867,
            "min": 1000.0,
            "max": 4000.0
        },
        {
            "current": 1000.381,
            "min": 1000.0,
            "max": 4000.0
        },
        {
            "current": 1000.777,
            "min": 1000.0,
            "max": 4000.0
        },
        {
            "current": 1000.466,
            "min": 1000.0,
            "max": 4000.0
        },
        {
            "current": 1000.091,
            "min": 1000.0,
            "max": 4000.0
        },
        {
            "current": 1000.215,
            "min": 1000.0,
            "max": 4000.0
        },
        {
            "current": 1000.329,
            "min": 1000.0,
            "max": 4000.0
        },
        {
            "current": 1000.452,
            "min": 1000.0,
            "max": 4000.0
        },
        {
            "current": 1000.29,
            "min": 1000.0,
            "max": 4000.0
        },
        {
            "current": 999.911,
            "min": 1000.0,
            "max": 4000.0
        },
        {
            "current": 1000.964,
            "min": 1000.0,
            "max": 4000.0
        },
        {
            "current": 1000.885,
            "min": 1000.0,
            "max": 4000.0
        },
        {
            "current": 1000.362,
            "min": 1000.0,
            "max": 4000.0
        },
        {
            "current": 1001.116,
            "min": 1000.0,
            "max": 4000.0
        },
        {
            "current": 1000.78,
            "min": 1000.0,
            "max": 4000.0
        },
        {
            "current": 1001.092,
            "min": 1000.0,
            "max": 4000.0
        },
        {
            "current": 1000.453,
            "min": 1000.0,
            "max": 4000.0
        },
        {
            "current": 1000.185,
            "min": 1000.0,
            "max": 4000.0
        },
        {
            "current": 1000.319,
            "min": 1000.0,
            "max": 4000.0
        },
        {
            "current": 1000.474,
            "min": 1000.0,
            "max": 4000.0
        },
        {
            "current": 1000.757,
            "min": 1000.0,
            "max": 4000.0
        },
        {
            "current": 1000.482,
            "min": 1000.0,
            "max": 4000.0
        },
        {
            "current": 1000.437,
            "min": 1000.0,
            "max": 4000.0
        },
        {
            "current": 1000.428,
            "min": 1000.0,
            "max": 4000.0
        },
        {
            "current": 1000.721,
            "min": 1000.0,
            "max": 4000.0
        },
        {
            "current": 1000.182,
            "min": 1000.0,
            "max": 4000.0
        },
        {
            "current": 1000.599,
            "min": 1000.0,
            "max": 4000.0
        },
        {
            "current": 999.899,
            "min": 1000.0,
            "max": 4000.0
        },
        {
            "current": 1000.524,
            "min": 1000.0,
            "max": 4000.0
        },
        {
            "current": 1000.49,
            "min": 1000.0,
            "max": 4000.0
        },
        {
            "current": 1000.533,
            "min": 1000.0,
            "max": 4000.0
        },
        {
            "current": 2585.612,
            "min": 1000.0,
            "max": 4000.0
        },
        {
            "current": 1000.549,
            "min": 1000.0,
            "max": 4000.0
        },
        {
            "current": 1000.515,
            "min": 1000.0,
            "max": 4000.0
        },
        {
            "current": 999.971,
            "min": 1000.0,
            "max": 4000.0
        },
        {
            "current": 1000.611,
            "min": 1000.0,
            "max": 4000.0
        },
        {
            "current": 1362.535,
            "min": 1000.0,
            "max": 4000.0
        },
        {
            "current": 1000.817,
            "min": 1000.0,
            "max": 4000.0
        },
        {
            "current": 1000.954,
            "min": 1000.0,
            "max": 4000.0
        },
        {
            "current": 999.901,
            "min": 1000.0,
            "max": 4000.0
        },
        {
            "current": 1000.443,
            "min": 1000.0,
            "max": 4000.0
        },
        {
            "current": 1000.186,
            "min": 1000.0,
            "max": 4000.0
        },
        {
            "current": 1000.335,
            "min": 1000.0,
            "max": 4000.0
        },
        {
            "current": 1000.379,
            "min": 1000.0,
            "max": 4000.0
        },
        {
            "current": 1000.038,
            "min": 1000.0,
            "max": 4000.0
        },
        {
            "current": 1000.744,
            "min": 1000.0,
            "max": 4000.0
        },
        {
            "current": 1000.463,
            "min": 1000.0,
            "max": 4000.0
        }
    ],
    "disk": {
        "/": {
            "total": 195.67869567871094,
            "used": 23.90427017211914
        }
    },
    "gpu": "NVIDIA RTX A6000",
    "gpu_count": 5,
    "gpu_devices": [
        {
            "name": "NVIDIA RTX A6000",
            "memory_total": 51050315776
        },
        {
            "name": "NVIDIA RTX A6000",
            "memory_total": 51050315776
        },
        {
            "name": "NVIDIA RTX A6000",
            "memory_total": 51050315776
        },
        {
            "name": "NVIDIA RTX A6000",
            "memory_total": 51050315776
        },
        {
            "name": "NVIDIA RTX A6000",
            "memory_total": 51050315776
        }
    ],
    "memory": {
        "total": 1510.522689819336
    }
}
